command_watcher/__init__.py
command_watcher/email.py
command_watcher/log.py
command_watcher/py.typed
command_watcher/report.py
command_watcher/utils.py
command_watcher-0.5.0.dist-info/LICENSE
command_watcher-0.5.0.dist-info/METADATA
command_watcher-0.5.0.dist-info/WHEEL
command_watcher-0.5.0.dist-info/RECORD
