Metadata-Version: 2.1
Name: command_watcher
Version: 0.5.0
Summary: Module to watch the execution of shell scripts. Both streams (`stdout` and `stderr`) are captured.
Home-page: https://github.com/Josef-Friedrich/command-watcher
License: MIT
Author: Josef Friedrich
Author-email: josef@friedrich.rocks
Requires-Python: >=3.10,<4.0
Classifier: Development Status :: 5 - Production/Stable
Classifier: License :: OSI Approved :: MIT License
Classifier: Programming Language :: Python :: 3
Classifier: Programming Language :: Python :: 3.10
Classifier: Programming Language :: Python :: 3.11
Classifier: Programming Language :: Python :: 3.12
Classifier: Programming Language :: Python :: 3 :: Only
Requires-Dist: conf2levels (>=0,<1)
Requires-Dist: pretiac (>=0,<1)
Requires-Dist: termcolor (>=1,<2)
Requires-Dist: types-requests (>=2,<3)
Requires-Dist: types-termcolor (>=1,<2)
Project-URL: Repository, https://github.com/Josef-Friedrich/command-watcher
